pythonvideoannotator_module_backgroundfinder/__init__.py
pythonvideoannotator_module_backgroundfinder/backgroundfinder_window.py
pythonvideoannotator_module_backgroundfinder/module.py
Python_video_annotator_module_background_finder-0.5.21.dist-info/METADATA
Python_video_annotator_module_background_finder-0.5.21.dist-info/WHEEL
Python_video_annotator_module_background_finder-0.5.21.dist-info/top_level.txt
Python_video_annotator_module_background_finder-0.5.21.dist-info/RECORD
