Metadata-Version: 2.1
Name: Python-video-annotator-module-background-finder
Version: 0.5.21
Summary: UNKNOWN
Home-page: https://bitbucket.org/fchampalimaud/pythonvideoannotator-module-backgroundfinder
Author: ['Ricardo Ribeiro']
Author-email: ricardojvr@gmail.com
License: UNKNOWN
Platform: UNKNOWN
